__init__.py
approvalWebAppBackendApiConnector.py
tim_approval_api_connector_test-0.0.1.dist-info/METADATA
tim_approval_api_connector_test-0.0.1.dist-info/WHEEL
tim_approval_api_connector_test-0.0.1.dist-info/licenses/license.txt
tim_approval_api_connector_test-0.0.1.dist-info/RECORD
