Metadata-Version: 2.1
Name: tim_approval_api_connector_test
Version: 0.0.1
Summary: test connector library
Author-email: Test <tuan4444c@gmail.com>
License-File: license.txt
Classifier: License :: OSI Approved :: MIT License
Classifier: Operating System :: OS Independent
Classifier: Programming Language :: Python :: 3
Requires-Python: >=3.7
